{
    "version": "0.4.0",
    "description": "Monte carlo combat simulation for Genshin Impact.",
    "homepage": "https://github.com/genshinsim/gcsimui/",
    "license": "Unknown",
    "architecture": {
        "64bit": {
            "url": "https://github.com/genshinsim/gcsimui/releases/download/gcsim-v0.4.0/gcsim_0.4.0_x64.msi",
            "hash": "60852f386deb199f5c7f8bb74249755faa4625ad06c782c3e1dcd0f433f03049"
        }
    },
    "shortcuts": [
        [
            "PFiles/gcsim/gcsim.exe",
            "gcsimui"
        ]
    ],
    "checkver": {
        "github": "https://github.com/genshinsim/gcsimui/",
        "regex": "/releases/tag/gcsim-v([\\d.]+)"
    },
    "autoupdate": {
        "architecture": {
            "64bit": {
                "url": "https://github.com/genshinsim/gcsimui/releases/download/gcsim-v$version/gcsim_$version_x64.msi"
            }
        }
    }
}
