{
    "version": "0.4.27",
    "description": "Monte carlo combat simulation for Genshin Impact.",
    "homepage": "https://github.com/genshinsim/gcsimui/",
    "license": "Unknown",
    "architecture": {
        "64bit": {
            "url": "https://github.com/genshinsim/gcsimui/releases/download/gcsim-v0.4.27/gcsim_0.4.27_x64.msi",
            "hash": "fa4dfea6a676f8948e8fc341e6d8bb00ff5e74bfbb8ecda7041513e66d29831b"
        }
    },
    "shortcuts": [
        [
            "PFiles/gcsim/gcsim.exe",
            "gcsimui"
        ]
    ],
    "checkver": {
        "github": "https://github.com/genshinsim/gcsimui/",
        "regex": "/releases/tag/gcsim-v([\\d.]+)"
    },
    "autoupdate": {
        "architecture": {
            "64bit": {
                "url": "https://github.com/genshinsim/gcsimui/releases/download/gcsim-v$version/gcsim_$version_x64.msi"
            }
        }
    }
}
